ekea/__init__.py
ekea/__main__.py
ekea/e3smapp.py
ekea/eam.py
ekea/exclude_e3sm_cam.ini
ekea/exclude_e3sm_eam.ini
ekea/exclude_e3sm_mpas.ini
ekea/exclude_e3sm_varlist.ini
ekea/main.py
ekea/mpasocn.py
ekea/timing.py
ekea/utils.py
ekea/varwhere.py
ekea-1.2.2.dist-info/LICENSE
ekea-1.2.2.dist-info/METADATA
ekea-1.2.2.dist-info/WHEEL
ekea-1.2.2.dist-info/entry_points.txt
ekea-1.2.2.dist-info/top_level.txt
ekea-1.2.2.dist-info/RECORD
